MANIFEST.in
README.md
setup.py
WebSocketCommandline/__init__.py
WebSocketCommandline.egg-info/PKG-INFO
WebSocketCommandline.egg-info/SOURCES.txt
WebSocketCommandline.egg-info/dependency_links.txt
WebSocketCommandline.egg-info/entry_points.txt
WebSocketCommandline.egg-info/requires.txt
WebSocketCommandline.egg-info/top_level.txt