Metadata-Version: 1.1
Name: WebSocketCommandline
Version: 0.0.8
Summary: A Python script to test WebSocket.
Home-page: https://github.com/owwlo/WebSocketCommandline
Author: owwlo
Author-email: owwlo.g@gmail.com
License: MIT
Download-URL: https://github.com/owwlo/WebSocketCommandline/tarball/0.0.8
Keywords: websocket test server client development
Platform: UNKNOWN
Classifier: Development Status :: 3 - Alpha
Classifier: Intended Audience :: Developers
Classifier: Topic :: Software Development
Classifier: License :: OSI Approved :: MIT License
Classifier: Programming Language :: Python :: 2
Classifier: Programming Language :: Python :: 2.6
Classifier: Programming Language :: Python :: 2.7
Classifier: Programming Language :: Python :: 3
Classifier: Programming Language :: Python :: 3.3
Classifier: Programming Language :: Python :: 3.4
Classifier: Programming Language :: Python :: 3.5
